README.md
pyproject.toml
setup.cfg
setup.py
tests/test_encryption_util.py
tests/test_querying.py
tests/test_refunds_service.py
tests/test_transaction_completions_service.py
tests/test_transactions_service.py
tests/test_webhook_listeners_api.py
wallee/__init__.py
wallee/api_client.py
wallee/api_exception_error_codes.py
wallee/api_response.py
wallee/configuration.py
wallee/exceptions.py
wallee/py.typed
wallee/rest.py
wallee/sdk_exception_error_codes.py
wallee/wallee_sdk_exception.py
wallee.egg-info/PKG-INFO
wallee.egg-info/SOURCES.txt
wallee.egg-info/dependency_links.txt
wallee.egg-info/requires.txt
wallee.egg-info/top_level.txt
wallee/models/__init__.py
wallee/models/abstract_account_update.py
wallee/models/abstract_application_user_update.py
wallee/models/abstract_customer_active.py
wallee/models/abstract_customer_address_active.py
wallee/models/abstract_customer_comment_active.py
wallee/models/abstract_debt_collection_case_update.py
wallee/models/abstract_debt_collector_configuration_update.py
wallee/models/abstract_human_user_update.py
wallee/models/abstract_payment_connector_configuration_update.py
wallee/models/abstract_payment_link_update.py
wallee/models/abstract_payment_method_configuration_update.py
wallee/models/abstract_payment_processor_configuration_active.py
wallee/models/abstract_payment_terminal_update.py
wallee/models/abstract_refund_comment_active.py
wallee/models/abstract_role_update.py
wallee/models/abstract_single_sign_on_user_update.py
wallee/models/abstract_space_update.py
wallee/models/abstract_subscriber_update.py
wallee/models/abstract_subscription_affiliate_update.py
wallee/models/abstract_subscription_metric_update.py
wallee/models/abstract_subscription_product_active.py
wallee/models/abstract_token_update.py
wallee/models/abstract_transaction_comment_active.py
wallee/models/abstract_transaction_invoice_comment_active.py
wallee/models/abstract_transaction_pending.py
wallee/models/abstract_webhook_listener_update.py
wallee/models/abstract_webhook_url_update.py
wallee/models/account.py
wallee/models/account_create.py
wallee/models/account_list_response.py
