Metadata-Version: 2.4
Name: wallee
Version: 6.3.0
Summary: Wallee Group AG API
Home-page: 
Author: wallee
Author-email: team@openapitools.org
Keywords: OpenAPI,OpenAPI-Generator,Wallee Group AG API
Classifier: Development Status :: 4 - Beta
Classifier: Programming Language :: Python :: 3.9
Classifier: Programming Language :: Python :: 3.10
Classifier: Programming Language :: Python :: 3.11
Classifier: Programming Language :: Python :: 3.12
Classifier: License :: OSI Approved :: Apache Software License
Classifier: Natural Language :: English
Classifier: Operating System :: OS Independent
Classifier: Intended Audience :: Developers
Classifier: Intended Audience :: Financial and Insurance Industry
Classifier: Topic :: Office/Business :: Financial :: Point-Of-Sale
Requires-Dist: pydantic>=2.10.4
Requires-Dist: PyJWT>=2.10.1
Requires-Dist: python-dateutil>=2.9.0.post0
Requires-Dist: typing-extensions>=4.12.2
Requires-Dist: urllib3<3,>=2.3
Requires-Dist: cryptography>=2.0
Provides-Extra: dev
Requires-Dist: flake8>=7.1.1; extra == "dev"
Requires-Dist: mypy>=1.14.1; extra == "dev"
Requires-Dist: pytest>=3.9; extra == "dev"
Requires-Dist: tox>=4.23.2; extra == "dev"
Requires-Dist: types-python-dateutil>=2.9.0.20241206; extra == "dev"
Dynamic: author
Dynamic: author-email
Dynamic: classifier
Dynamic: description
Dynamic: description-content-type
Dynamic: keywords
Dynamic: provides-extra
Dynamic: requires-dist
Dynamic: summary
